{
    "key": "group_68dee3fc740cc",
    "title": "Kids Cards Section",
    "fields": [
        {
            "key": "field_68dee3fc81bb6",
            "label": "Kids Cards",
            "name": "kids_cards",
            "aria-label": "",
            "type": "repeater",
            "instructions": "",
            "required": 0,
            "conditional_logic": 0,
            "wrapper": {
                "width": "",
                "class": "",
                "id": ""
            },
            "layout": "table",
            "pagination": 0,
            "min": 0,
            "max": 0,
            "collapsed": "",
            "button_label": "Add Row",
            "rows_per_page": 20,
            "sub_fields": [
                {
                    "key": "field_68dee42981bb7",
                    "label": "Kid Card Image",
                    "name": "kid_card_image",
                    "aria-label": "",
                    "type": "image",
                    "instructions": "",
                    "required": 0,
                    "conditional_logic": 0,
                    "wrapper": {
                        "width": "",
                        "class": "",
                        "id": ""
                    },
                    "return_format": "array",
                    "library": "all",
                    "min_width": "",
                    "min_height": "",
                    "min_size": "",
                    "max_width": "",
                    "max_height": "",
                    "max_size": "",
                    "mime_types": "",
                    "allow_in_bindings": 0,
                    "preview_size": "medium",
                    "parent_repeater": "field_68dee3fc81bb6"
                },
                {
                    "key": "field_68dee47681bb8",
                    "label": "Collected Amount",
                    "name": "collected_amount",
                    "aria-label": "",
                    "type": "number",
                    "instructions": "",
                    "required": 0,
                    "conditional_logic": 0,
                    "wrapper": {
                        "width": "",
                        "class": "",
                        "id": ""
                    },
                    "default_value": "",
                    "min": "",
                    "max": "",
                    "allow_in_bindings": 0,
                    "placeholder": "",
                    "step": "",
                    "prepend": "",
                    "append": "",
                    "parent_repeater": "field_68dee3fc81bb6"
                },
                {
                    "key": "field_68dee48c81bb9",
                    "label": "Required Amount",
                    "name": "required_amount",
                    "aria-label": "",
                    "type": "number",
                    "instructions": "",
                    "required": 0,
                    "conditional_logic": 0,
                    "wrapper": {
                        "width": "",
                        "class": "",
                        "id": ""
                    },
                    "default_value": "",
                    "min": "",
                    "max": "",
                    "allow_in_bindings": 0,
                    "placeholder": "",
                    "step": "",
                    "prepend": "",
                    "append": "",
                    "parent_repeater": "field_68dee3fc81bb6"
                },
                {
                    "key": "field_68dee4bf81bba",
                    "label": "Kid Name",
                    "name": "kid_name",
                    "aria-label": "",
                    "type": "textarea",
                    "instructions": "",
                    "required": 0,
                    "conditional_logic": 0,
                    "wrapper": {
                        "width": "",
                        "class": "",
                        "id": ""
                    },
                    "default_value": "",
                    "maxlength": "",
                    "allow_in_bindings": 0,
                    "rows": "",
                    "placeholder": "",
                    "new_lines": "",
                    "parent_repeater": "field_68dee3fc81bb6"
                },
                {
                    "key": "field_68dee4e881bbb",
                    "label": "Kid Age",
                    "name": "kid_age",
                    "aria-label": "",
                    "type": "textarea",
                    "instructions": "",
                    "required": 0,
                    "conditional_logic": 0,
                    "wrapper": {
                        "width": "",
                        "class": "",
                        "id": ""
                    },
                    "default_value": "",
                    "maxlength": "",
                    "allow_in_bindings": 0,
                    "rows": "",
                    "placeholder": "",
                    "new_lines": "",
                    "parent_repeater": "field_68dee3fc81bb6"
                },
                {
                    "key": "field_68dee4f781bbc",
                    "label": "Kid Diagnosis",
                    "name": "kid_diagnosis",
                    "aria-label": "",
                    "type": "textarea",
                    "instructions": "",
                    "required": 0,
                    "conditional_logic": 0,
                    "wrapper": {
                        "width": "",
                        "class": "",
                        "id": ""
                    },
                    "default_value": "",
                    "maxlength": "",
                    "allow_in_bindings": 0,
                    "rows": "",
                    "placeholder": "",
                    "new_lines": "",
                    "parent_repeater": "field_68dee3fc81bb6"
                },
                {
                    "key": "field_68dee51e81bbd",
                    "label": "Donate BTN Link",
                    "name": "donate_btn_link",
                    "aria-label": "",
                    "type": "textarea",
                    "instructions": "",
                    "required": 0,
                    "conditional_logic": 0,
                    "wrapper": {
                        "width": "",
                        "class": "",
                        "id": ""
                    },
                    "default_value": "",
                    "maxlength": "",
                    "allow_in_bindings": 0,
                    "rows": "",
                    "placeholder": "",
                    "new_lines": "",
                    "parent_repeater": "field_68dee3fc81bb6"
                },
                {
                    "key": "field_68dee53281bbe",
                    "label": "More About a Child Link",
                    "name": "more_about_a_child_link",
                    "aria-label": "",
                    "type": "textarea",
                    "instructions": "",
                    "required": 0,
                    "conditional_logic": 0,
                    "wrapper": {
                        "width": "",
                        "class": "",
                        "id": ""
                    },
                    "default_value": "",
                    "maxlength": "",
                    "allow_in_bindings": 0,
                    "rows": "",
                    "placeholder": "",
                    "new_lines": "",
                    "parent_repeater": "field_68dee3fc81bb6"
                }
            ]
        }
    ],
    "location": [
        [
            {
                "param": "page",
                "operator": "==",
                "value": "9"
            }
        ]
    ],
    "menu_order": 0,
    "position": "normal",
    "style": "default",
    "label_placement": "top",
    "instruction_placement": "label",
    "hide_on_screen": "",
    "active": true,
    "description": "",
    "show_in_rest": 0,
    "modified": 1759438370
}
